tg_logger/__init__.py
tg_logger/files.py
tg_logger/handler.py
tg_logger-3.3.dist-info/LICENSE
tg_logger-3.3.dist-info/METADATA
tg_logger-3.3.dist-info/WHEEL
tg_logger-3.3.dist-info/top_level.txt
tg_logger-3.3.dist-info/RECORD
