Metadata-Version: 2.1
Name: tg-logger
Version: 3.3
Summary: A tool to bridge python logging and user files to telegram bot
Home-page: https://github.com/otter18/tg_logger
Author: ChernV (otter18)
Author-email: vchern185@gmail.com
License: UNKNOWN
Platform: UNKNOWN
Classifier: Programming Language :: Python :: 3
Classifier: License :: OSI Approved :: MIT License
Classifier: Operating System :: OS Independent
Requires-Python: >=3.6
License-File: LICENSE
Requires-Dist: pyTelegramBotAPI (>=3.7.6)
